dagster_hashicorp/__init__.py
dagster_hashicorp/py.typed
dagster_hashicorp/vault/__init__.py
dagster_hashicorp/vault/resources.py
dagster_hashicorp/vault/secrets.py
dagster_hashicorp-0.1.1.dist-info/LICENSE
dagster_hashicorp-0.1.1.dist-info/METADATA
dagster_hashicorp-0.1.1.dist-info/WHEEL
dagster_hashicorp-0.1.1.dist-info/top_level.txt
dagster_hashicorp-0.1.1.dist-info/RECORD
