Metadata-Version: 2.1
Name: dagster-hashicorp
Version: 0.1.1
Summary: Package for integrating Hashicorp Vault with Dagster.
Home-page: https://github.com/silentsokolov/dagster-hashicorp
Author: Dmitriy Sokolov
Author-email: silentsokolov@gmail.com
License: MIT
Keywords: dagster,hashicorp,vault
Platform: any
Classifier: Development Status :: 5 - Production/Stable
Classifier: Intended Audience :: Developers
Classifier: License :: OSI Approved :: MIT License
Classifier: Programming Language :: Python :: 3.6
Classifier: Programming Language :: Python :: 3.7
Classifier: Programming Language :: Python :: 3.8
Classifier: Programming Language :: Python :: 3.9
Requires-Python: >=3.6
License-File: LICENSE
Requires-Dist: hvac
